example_package_mchiuminatto/__init__.py
example_package_mchiuminatto/example.py
thequantick_package_test-0.0.1.dist-info/LICENSE
thequantick_package_test-0.0.1.dist-info/METADATA
thequantick_package_test-0.0.1.dist-info/WHEEL
thequantick_package_test-0.0.1.dist-info/top_level.txt
thequantick_package_test-0.0.1.dist-info/RECORD
