Metadata-Version: 2.1
Name: thequantick_package_test
Version: 0.0.1
Summary: small descrioption
Author-email: Marcello Chiuminatto <mchiuminatto@gmail.com>
Project-URL: Homepage, http://github.com/pypa/sampleproject
Project-URL: Issues, http://github.com/pypa/sampleproject/issues
Classifier: Programming Language :: Python :: 3
Classifier: License :: OSI Approved :: MIT License
Classifier: Operating System :: OS Independent
Requires-Python: >=3.11
License-File: LICENSE
Requires-Dist: numpy ==1.26.4
Requires-Dist: pandas ==2.2.1
Requires-Dist: python-dateutil ==2.8.2
Requires-Dist: pytz ==2024.1
Requires-Dist: six ==1.16.0
Requires-Dist: tzdata ==2024.1
